mcpbr/__init__.py
mcpbr/__main__.py
mcpbr/agent.py
mcpbr/cache.py
mcpbr/cli.py
mcpbr/config.py
mcpbr/config_inheritance.py
mcpbr/config_validator.py
mcpbr/docker_env.py
mcpbr/env_expansion.py
mcpbr/evaluation.py
mcpbr/harness.py
mcpbr/harnesses.py
mcpbr/incremental_save.py
mcpbr/junit_reporter.py
mcpbr/log_formatter.py
mcpbr/models.py
mcpbr/output_validator.py
mcpbr/preflight.py
mcpbr/pricing.py
mcpbr/profiler.py
mcpbr/providers.py
mcpbr/regression.py
mcpbr/reporting.py
mcpbr/schema.py
mcpbr/smoke_test.py
mcpbr/state_tracker.py
mcpbr/statistics.py
mcpbr/streaming.py
mcpbr/templates.py
mcpbr/benchmarks/__init__.py
mcpbr/benchmarks/base.py
mcpbr/benchmarks/cybergym.py
mcpbr/benchmarks/humaneval.py
mcpbr/benchmarks/mcptoolbench.py
mcpbr/benchmarks/swebench.py
mcpbr/data/templates/brave-search.yaml
mcpbr/data/templates/filesystem.yaml
mcpbr/data/templates/github.yaml
mcpbr/data/templates/google-maps.yaml
mcpbr/data/templates/postgres.yaml
mcpbr/data/templates/slack.yaml
mcpbr/data/templates/sqlite.yaml
mcpbr-0.4.2.data/data/mcpbr/data/templates/brave-search.yaml
mcpbr-0.4.2.data/data/mcpbr/data/templates/filesystem.yaml
mcpbr-0.4.2.data/data/mcpbr/data/templates/github.yaml
mcpbr-0.4.2.data/data/mcpbr/data/templates/google-maps.yaml
mcpbr-0.4.2.data/data/mcpbr/data/templates/postgres.yaml
mcpbr-0.4.2.data/data/mcpbr/data/templates/slack.yaml
mcpbr-0.4.2.data/data/mcpbr/data/templates/sqlite.yaml
mcpbr-0.4.2.dist-info/METADATA
mcpbr-0.4.2.dist-info/WHEEL
mcpbr-0.4.2.dist-info/entry_points.txt
mcpbr-0.4.2.dist-info/licenses/LICENSE
mcpbr-0.4.2.dist-info/RECORD
