Metadata-Version: 2.4
Name: mcpbr
Version: 0.4.2
Summary: Model Context Protocol Benchmark Runner - evaluate MCP servers against software engineering benchmarks
Project-URL: Homepage, https://github.com/greynewell/mcpbr
Project-URL: Repository, https://github.com/greynewell/mcpbr
Project-URL: Documentation, https://greynewell.github.io/mcpbr/
Project-URL: Changelog, https://github.com/greynewell/mcpbr/blob/main/CHANGELOG.md
Project-URL: Bug Tracker, https://github.com/greynewell/mcpbr/issues
Author: mcpbr Contributors
License-Expression: MIT
License-File: LICENSE
Keywords: agents,benchmark,cybergym,evaluation,llm,mcp,model-context-protocol,security,swe-bench
Classifier: Development Status :: 3 - Alpha
Classifier: Intended Audience :: Developers
Classifier: License :: OSI Approved :: MIT License
Classifier: Programming Language :: Python :: 3
Classifier: Programming Language :: Python :: 3.11
Classifier: Programming Language :: Python :: 3.12
Requires-Python: >=3.11
Requires-Dist: anthropic>=0.40.0
Requires-Dist: click>=8.0.0
Requires-Dist: datasets>=2.14.0
Requires-Dist: docker>=7.0.0
Requires-Dist: mcp>=1.0.0
Requires-Dist: psutil>=5.9.0
Requires-Dist: pydantic-settings>=2.0.0
Requires-Dist: pydantic>=2.0.0
Requires-Dist: pyyaml>=6.0.0
Requires-Dist: requests>=2.31.0
Requires-Dist: rich>=13.0.0
Provides-Extra: dev
Requires-Dist: pre-commit>=3.0.0; extra == 'dev'
Requires-Dist: pytest-asyncio>=0.21.0; extra == 'dev'
Requires-Dist: pytest>=9.0.2; extra == 'dev'
Requires-Dist: ruff>=0.1.0; extra == 'dev'
Provides-Extra: docs
Requires-Dist: mkdocs-material>=9.5.0; extra == 'docs'
Requires-Dist: mkdocs-minify-plugin>=0.7.0; extra == 'docs'
Requires-Dist: mkdocs>=1.5.0; extra == 'docs'
Requires-Dist: mkdocstrings[python]>=0.24.0; extra == 'docs'
